typecastai/__init__.py
typecastai/actor.py
typecastai/client.py
typecastai/error.py
typecastai-0.1.3.dist-info/METADATA
typecastai-0.1.3.dist-info/WHEEL
typecastai-0.1.3.dist-info/RECORD
