Metadata-Version: 2.1
Name: typecastai
Version: 0.1.3
Summary: typecast.ai api
Home-page: https://typecast.ai/
Keywords: typecastai,ssfm,typecast,ai,tts,speech,text,generative
Author: Juncheol Cho
Author-email: zironycho@neosapience.com
Requires-Python: >=3.8,<4.0
Classifier: Programming Language :: Python :: 3
Classifier: Programming Language :: Python :: 3.8
Classifier: Programming Language :: Python :: 3.9
Classifier: Programming Language :: Python :: 3.10
Classifier: Programming Language :: Python :: 3.11
Classifier: Programming Language :: Python :: 3.12
Requires-Dist: requests (>=2.31.0,<3.0.0)
Project-URL: Documentation, https://docs.typecast.ai
Project-URL: Repository, https://github.com/neosapience/typecast-python
